simple_lambda/__init__.py
simple_lambda/cli.py
simple_lambda/py.typed
simple_lambda-0.1.0.dist-info/WHEEL
simple_lambda-0.1.0.dist-info/entry_points.txt
simple_lambda-0.1.0.dist-info/METADATA
simple_lambda-0.1.0.dist-info/RECORD
