Metadata-Version: 2.3
Name: simple-lambda
Version: 0.1.0
Summary: Simplify your lambda workflow
Author-email: jamie.cheng.chang@gmail.com
License:                                  Apache License
Requires-Dist: boto3>=1.40.21
Requires-Dist: typer>=0.17.3
Requires-Python: >=3.13
